CHANGES.txt
LICENSE
MANIFEST.in
README.md
setup.py
langner/__init__.py
langner/ast.py
langner/lexer.py
langner/parser.py
langner/tokenizer.py
langner.egg-info/PKG-INFO
langner.egg-info/SOURCES.txt
langner.egg-info/dependency_links.txt
langner.egg-info/requires.txt
langner.egg-info/top_level.txt
langner.egg-info/zip-safe