Metadata-Version: 1.0
Name: langner
Version: 0.2
Summary: Langner - language for expressing behaviour strategies.
Home-page: https://github.com/romankierzkowski/langner
Author: Roman Kierzkowski
Author-email: roman.kierzkowski@gmail.com
License: MIT
Keywords: langner strategies strategy logic
Platform: UNKNOWN
Classifier: Development Status :: 3 - Alpha
Classifier: License :: OSI Approved :: MIT License
Classifier: Programming Language :: Python :: 2.7
Classifier: Topic :: Scientific/Engineering :: Artificial Intelligence
Classifier: Intended Audience :: Science/Research
